dump/display7Segment/disp7s.v
// Управление 7-сгементным индикатором
module disp7s(
    input [3:0]     in,
    output reg [6:0]    out
);
    always @(*) begin
        case(in)
            4'd00: out = 7'b111_1110;
            4'd01: out = 7'b011_0000;
            4'd02: out = 7'b110_1101;
            4'd03: out = 7'b111_1001;
            4'd04: out = 7'b011_0011;
            4'd05: out = 7'b101_1011;
            4'd06: out = 7'b101_1111;
            4'd07: out = 7'b111_0000;
            4'd08: out = 7'b111_1111;
            4'd09: out = 7'b111_1011;
            4'd10: out = 7'b111_0111;
            4'd11: out = 7'b001_1111;
            4'd12: out = 7'b100_1110;
            4'd13: out = 7'b011_1101;
            4'd14: out = 7'b100_1111;
            4'd15: out = 7'b100_0111;
            default: out = 7'b000_0000;
        endcase
    end
endmodule

display7Segment/test.v
module test;
    reg [3:0] in;
    wire [6:0] out;

    disp7s testee(.in(in), .out(out));
    initial begin
        $dumpfile("dump.vcd");
        $dumpvars(0, test);
    end

    always #1 in += 1;
    initial #1 in = 0;
    initial #17 $finish;
endmodule

drafts/display7Segment/dump.vcd
$date
	Mon Nov  4 16:28:00 2019
$end
$version
	Icarus Verilog
$end
$timescale
	1s
$end
$scope module test $end
$var wire 7 ! out [6:0] $end
$var reg 4 " in [3:0] $end
$scope module testee $end
$var wire 4 # in [3:0] $end
$var reg 7 $ out [6:0] $end
$upscope $end
$upscope $end
$enddefinitions $end
#0
$dumpvars
bx $
bx #
bx "
bx !
$end
#1
b1111110 !
b1111110 $
b0 "
b0 #
#2
b110000 !
b110000 $
b1 "
b1 #
#3
b1101101 !
b1101101 $
b10 "
b10 #
#4
b1111001 !
b1111001 $
b11 "
b11 #
#5
b110011 !
b110011 $
b100 "
b100 #
#6
b1011011 !
b1011011 $
b101 "
b101 #
#7
b1011111 !
b1011111 $
b110 "
b110 #
#8
b1110000 !
b1110000 $
b111 "
b111 #
#9
b1111111 !
b1111111 $
b1000 "
b1000 #
#10
b1111011 !
b1111011 $
b1001 "
b1001 #
#11
b1110111 !
b1110111 $
b1010 "
b1010 #
#12
b11111 !
b11111 $
b1011 "
b1011 #
#13
b1001110 !
b1001110 $
b1100 "
b1100 #
#14
b111101 !
b111101 $
b1101 "
b1101 #
#15
b1001111 !
b1001111 $
b1110 "
b1110 #
#16
b1000111 !
b1000111 $
b1111 "
b1111 #
#17
b1111110 !
b1111110 $
b0 "
b0 #
